visbeat3/ADefines.py
visbeat3/AFileManager.py
visbeat3/AFuncDict.py
visbeat3/AImports.py
visbeat3/AObject.py
visbeat3/AParamDict.py
visbeat3/Audio.py
visbeat3/AudioClip.py
visbeat3/Event.py
visbeat3/EventList.py
visbeat3/Image.py
visbeat3/Image_CV.py
visbeat3/SourceLocationParser.py
visbeat3/TimeSignal.py
visbeat3/TimeSignal1D.py
visbeat3/VBMIDI.py
visbeat3/VBObject.py
visbeat3/Video.py
visbeat3/VideoClip.py
visbeat3/VideoSource.py
visbeat3/Video_CV.py
visbeat3/VisBeatDefines.py
visbeat3/VisBeatExampleVideo.py
visbeat3/VisBeatImports.py
visbeat3/VisualBeat.py
visbeat3/Warp.py
visbeat3/__init__.py
visbeat3/_dancefer_examples.py
visbeat3/_dancify_examples.py
visbeat3/_mediafiles.py
visbeat3/_music_examples.py
visbeat3/command_line.py
visbeat3/assets/audio/hit.wav
visbeat3/assets/images/VisBeatWatermark.png
visbeat3/fileui/__init__.py
visbeat3/fileui/uipath.py
visbeat3/fileui/__pycache__/__init__.cpython-39.pyc
visbeat3/vbgui/BeatGUI.py
visbeat3/vbgui/__init__.py
visbeat3/vbgui/__pycache__/BeatGUI.cpython-39.pyc
visbeat3/vbgui/__pycache__/__init__.cpython-39.pyc
visbeat3-1.0.1.data/scripts/dancefer
visbeat3-1.0.1.dist-info/LICENSE
visbeat3-1.0.1.dist-info/METADATA
visbeat3-1.0.1.dist-info/WHEEL
visbeat3-1.0.1.dist-info/top_level.txt
visbeat3-1.0.1.dist-info/RECORD
