Metadata-Version: 2.1
Name: visbeat3
Version: 1.0.1
Summary: Python3 Implementation for 'Visual Rhythm and Beat' SIGGRAPH 2018
Home-page: https://github.com/haofanwang/visbeat3
Author: Haofan Wang
Author-email: haofanwang.ai@gmail.com
Classifier: Programming Language :: Python :: 3
Classifier: License :: OSI Approved :: Apache Software License
Classifier: Operating System :: OS Independent
License-File: LICENSE
Requires-Dist: numpy
Requires-Dist: scipy
Requires-Dist: bs4
Requires-Dist: librosa (==0.9.1)
Requires-Dist: imageio (==2.9.0)
Requires-Dist: imageio-ffmpeg (==0.4.5)
Requires-Dist: requests
Requires-Dist: moviepy (==1.0.3)
Requires-Dist: termcolor
Requires-Dist: youtube-dl
Requires-Dist: matplotlib
Requires-Dist: opencv-python
